transformers_utils/__init__.py
transformers_utils/data.py
transformers_utils/datatype.py
transformers_utils-0.0.1.dist-info/licenses/LICENSE
transformers_utils-0.0.1.dist-info/METADATA
transformers_utils-0.0.1.dist-info/WHEEL
transformers_utils-0.0.1.dist-info/top_level.txt
transformers_utils-0.0.1.dist-info/RECORD
