Metadata-Version: 2.4
Name: transformers_utils
Version: 0.0.1
Summary: Individual researcher's LLM training solution based on transformers, covering both pre-training and post-training.
License-Expression: Apache-2.0
Classifier: Programming Language :: Python :: 3
Classifier: Operating System :: OS Independent
Requires-Python: >=3.9
License-File: LICENSE
Dynamic: license-file
